fink_filters/__init__.py
fink_filters/tester.py
fink_filters/data/list_dwarfs_AGN_RADEC.parquet
fink_filters/data/magnetic_cataclysmic_variables.csv
fink_filters/data/mangrove_filtered.csv
fink_filters/data/symbiotic_and_cataclysmic.parquet
fink_filters/data/tde.parquet
fink_filters/rubin/__init__.py
fink_filters/rubin/blocks.py
fink_filters/rubin/filter_extragalactic_rising_candidate/__init__.py
fink_filters/rubin/filter_extragalactic_rising_candidate/filter.py
fink_filters/rubin/livestream/__init__.py
fink_filters/rubin/livestream/filter_cataloged/__init__.py
fink_filters/rubin/livestream/filter_cataloged/filter.py
fink_filters/rubin/livestream/filter_extragalactic_candidate/__init__.py
fink_filters/rubin/livestream/filter_extragalactic_candidate/filter.py
fink_filters/rubin/livestream/filter_in_tns/__init__.py
fink_filters/rubin/livestream/filter_in_tns/filter.py
fink_filters/ztf/__init__.py
fink_filters/ztf/classification.py
fink_filters/ztf/filter_anomaly_notification/__init__.py
fink_filters/ztf/filter_anomaly_notification/filter.py
fink_filters/ztf/filter_anomaly_notification/filter_utils.py
fink_filters/ztf/filter_blazar_low_state/__init__.py
fink_filters/ztf/filter_blazar_low_state/filter.py
fink_filters/ztf/filter_blazar_new_low_state/__init__.py
fink_filters/ztf/filter_blazar_new_low_state/filter.py
fink_filters/ztf/filter_dwarf_agn/__init__.py
fink_filters/ztf/filter_dwarf_agn/filter.py
fink_filters/ztf/filter_early_tde_candidates/__init__.py
fink_filters/ztf/filter_early_tde_candidates/filter.py
fink_filters/ztf/filter_early_tde_candidates/lcs.py
fink_filters/ztf/filter_early_tde_candidates/prefilter.py
fink_filters/ztf/filter_early_tde_candidates/data/model_broad.ubj
fink_filters/ztf/filter_early_tde_candidates/data/model_nuclear.ubj
fink_filters/ztf/filter_example/__init__.py
fink_filters/ztf/filter_example/filter.py
fink_filters/ztf/filter_gaia_candidates/__init__.py
fink_filters/ztf/filter_gaia_candidates/filter.py
fink_filters-7.18.dist-info/LICENSE
fink_filters-7.18.dist-info/METADATA
fink_filters-7.18.dist-info/WHEEL
fink_filters-7.18.dist-info/top_level.txt
fink_filters-7.18.dist-info/RECORD
